diamond_ci_exam/__init__.py
diamond_ci_exam/diamond_ci_exam.py
diamond_ci_exam-0.1.8.dist-info/METADATA
diamond_ci_exam-0.1.8.dist-info/WHEEL
diamond_ci_exam-0.1.8.dist-info/RECORD
