Metadata-Version: 2.1
Name: diamond_ci_exam
Version: 0.1.8
Summary: "Create a diamond from a letter."
Author: Dimitri Perreaux
Author-email: dimitri.perreaux@gmail.com
Requires-Python: >=3.9,<4.0
Classifier: Programming Language :: Python :: 3
Classifier: Programming Language :: Python :: 3.9
Classifier: Programming Language :: Python :: 3.10
Classifier: Programming Language :: Python :: 3.11
Classifier: Programming Language :: Python :: 3.12
Requires-Dist: flake8 (>=6.1.0,<7.0.0)
Requires-Dist: flake8-bandit (>=4.1.1,<5.0.0)
Requires-Dist: flake8-isort (>=6.1.1,<7.0.0)
